<?xml version="1.0" encoding="utf-8" ?><dwsync><file name="bootstrap.js" server="ftp.donaldheyd.com//public_html/interact2017/" local="3563877264" remote="3563963580" Dst="-1" /><file name="bootstrap.min.js" server="ftp.donaldheyd.com//public_html/interact2017/" local="3563877264" remote="3563963580" Dst="-1" /><file name="datatable.js" server="ftp.donaldheyd.com//public_html/interact2017/" local="3563877264" remote="3563963580" Dst="-1" /><file name="datatable.min.js" server="ftp.donaldheyd.com//public_html/interact2017/" local="3563877264" remote="3563963580" Dst="-1" /><file name="editable.js" server="ftp.donaldheyd.com//public_html/interact2017/" local="3563877264" remote="3563963580" Dst="-1" /><file name="editable.min.js" server="ftp.donaldheyd.com//public_html/interact2017/" local="3563877264" remote="3563963580" Dst="-1" /><file name="footable.min.js" server="ftp.donaldheyd.com//public_html/interact2017/" local="3563877264" remote="3563963580" Dst="-1" /><file name="jqtabledit.js" server="ftp.donaldheyd.com//public_html/interact2017/" local="3563877264" remote="3563963580" Dst="-1" /><file name="footable.js" server="ftp.donaldheyd.com//public_html/interact2017/" local="3563877264" remote="3563963580" Dst="-1" /><file name="jqtabledit.min.js" server="ftp.donaldheyd.com//public_html/interact2017/" local="3563877264" remote="3563963580" Dst="-1" /><file name="jsgrid-db.min.js" server="ftp.donaldheyd.com//public_html/interact2017/" local="3563877265" remote="3563963580" Dst="-1" /><file name="jsgrid-db.js" server="ftp.donaldheyd.com//public_html/interact2017/" local="3563877264" remote="3563963580" Dst="-1" /><file name="jsgrid.min.js" server="ftp.donaldheyd.com//public_html/interact2017/" local="3563877265" remote="3563963580" Dst="-1" /><file name="jsgrid.js" server="ftp.donaldheyd.com//public_html/interact2017/" local="3563877264" remote="3563963580" Dst="-1" /><file name="bootstrap.js" server="ftp.donaldheyd.com//public_html/_intdru/" local="3563877264" remote="3571437180" Dst="-1" /><file name="bootstrap.min.js" server="ftp.donaldheyd.com//public_html/_intdru/" local="3563877264" remote="3571437180" Dst="-1" /><file name="datatable.js" server="ftp.donaldheyd.com//public_html/_intdru/" local="3563877264" remote="3571437180" Dst="-1" /><file name="datatable.min.js" server="ftp.donaldheyd.com//public_html/_intdru/" local="3563877264" remote="3571437180" Dst="-1" /><file name="editable.min.js" server="ftp.donaldheyd.com//public_html/_intdru/" local="3563877264" remote="3571437180" Dst="-1" /><file name="footable.js" server="ftp.donaldheyd.com//public_html/_intdru/" local="3563877264" remote="3571437180" Dst="-1" /><file name="editable.js" server="ftp.donaldheyd.com//public_html/_intdru/" local="3563877264" remote="3571437180" Dst="-1" /><file name="footable.min.js" server="ftp.donaldheyd.com//public_html/_intdru/" local="3563877264" remote="3571437180" Dst="-1" /><file name="jqtabledit.min.js" server="ftp.donaldheyd.com//public_html/_intdru/" local="3563877264" remote="3571437180" Dst="-1" /><file name="jqtabledit.js" server="ftp.donaldheyd.com//public_html/_intdru/" local="3563877264" remote="3571437180" Dst="-1" /><file name="jsgrid-db.js" server="ftp.donaldheyd.com//public_html/_intdru/" local="3563877264" remote="3571437180" Dst="-1" /><file name="jsgrid-db.min.js" server="ftp.donaldheyd.com//public_html/_intdru/" local="3563877265" remote="3571437180" Dst="-1" /><file name="jsgrid.js" server="ftp.donaldheyd.com//public_html/_intdru/" local="3563877264" remote="3571437180" Dst="-1" /><file name="jsgrid.min.js" server="ftp.donaldheyd.com//public_html/_intdru/" local="3563877265" remote="3571437180" Dst="-1" /></dwsync>