<?xml version="1.0" encoding="utf-8" ?><dwsync><file name="overrides-cerulean.min.css" server="ftp.donaldheyd.com//public_html/_intdru/" local="3571393740" remote="3571390200" Dst="-1" /><file name="overrides-cosmo.min.css" server="ftp.donaldheyd.com//public_html/_intdru/" local="3571393740" remote="3571390200" Dst="-1" /><file name="overrides-cyborg.min.css" server="ftp.donaldheyd.com//public_html/_intdru/" local="3571393740" remote="3571390200" Dst="-1" /><file name="overrides-darkly.min.css" server="ftp.donaldheyd.com//public_html/_intdru/" local="3571393741" remote="3571390200" Dst="-1" /><file name="overrides-journal.min.css" server="ftp.donaldheyd.com//public_html/_intdru/" local="3571393741" remote="3571390200" Dst="-1" /><file name="overrides-flatly.min.css" server="ftp.donaldheyd.com//public_html/_intdru/" local="3571393741" remote="3571390200" Dst="-1" /><file name="overrides-lumen.min.css" server="ftp.donaldheyd.com//public_html/_intdru/" local="3571393741" remote="3571390200" Dst="-1" /><file name="overrides-paper.min.css" server="ftp.donaldheyd.com//public_html/_intdru/" local="3571393742" remote="3571390200" Dst="-1" /><file name="overrides-readable.min.css" server="ftp.donaldheyd.com//public_html/_intdru/" local="3571393742" remote="3571390200" Dst="-1" /><file name="overrides-sandstone.min.css" server="ftp.donaldheyd.com//public_html/_intdru/" local="3571393742" remote="3571390200" Dst="-1" /><file name="overrides-simplex.min.css" server="ftp.donaldheyd.com//public_html/_intdru/" local="3571393743" remote="3571390200" Dst="-1" /><file name="overrides-slate.min.css" server="ftp.donaldheyd.com//public_html/_intdru/" local="3571393743" remote="3571390200" Dst="-1" /><file name="overrides-spacelab.min.css" server="ftp.donaldheyd.com//public_html/_intdru/" local="3571393743" remote="3571390200" Dst="-1" /><file name="overrides-superhero.min.css" server="ftp.donaldheyd.com//public_html/_intdru/" local="3571393744" remote="3571390200" Dst="-1" /><file name="overrides-united.min.css" server="ftp.donaldheyd.com//public_html/_intdru/" local="3571393744" remote="3571390200" Dst="-1" /><file name="overrides-yeti.min.css" server="ftp.donaldheyd.com//public_html/_intdru/" local="3571393744" remote="3571390200" Dst="-1" /><file name="overrides.min.css" server="ftp.donaldheyd.com//public_html/_intdru/" local="3571393745" remote="3571390200" Dst="-1" /></dwsync>